README.rst
setup.py
EpiTator.egg-info/PKG-INFO
EpiTator.egg-info/SOURCES.txt
EpiTator.egg-info/dependency_links.txt
EpiTator.egg-info/requires.txt
EpiTator.egg-info/top_level.txt
epitator/__init__.py
epitator/annodoc.py
epitator/annospan.py
epitator/annotator.py
epitator/annotier.py
epitator/count_annotator.py
epitator/database_interface.py
epitator/date_annotator.py
epitator/disease_annotator.py
epitator/geoname_annotator.py
epitator/geoname_classifier.py
epitator/get_database_connection.py
epitator/incident_annotator.py
epitator/infection_annotator.py
epitator/maximum_weight_interval_set.py
epitator/metaspan.py
epitator/ne_annotator.py
epitator/ngram_annotator.py
epitator/pos_annotator.py
epitator/raw_number_annotator.py
epitator/resolved_keyword_annotator.py
epitator/spacy_annotator.py
epitator/spacy_nlp.py
epitator/species_annotator.py
epitator/structured_data_annotator.py
epitator/structured_incident_annotator.py
epitator/token_annotator.py
epitator/utils.py
epitator/version.py
epitator/importers/__init__.py
epitator/importers/import_all.py
epitator/importers/import_disease_ontology.py
epitator/importers/import_geonames.py
epitator/importers/import_species.py
epitator/importers/import_wikidata.py