Metadata-Version: 1.1
Name: EpiTator
Version: 1.3.5
Summary: Annotators for extracting epidemiological information from text.
Home-page: https://github.com/ecohealthalliance/EpiTator
Author: EcoHealth Alliance
Author-email: breit@ecohealthalliance.org
License: UNKNOWN
Keywords: nlp information extraction case counts death counts count extraction date extraction epidemiology keyword resolution toponym resolution disease resolution species resolution geoannotation geoname resolution
Platform: UNKNOWN
Classifier: Topic :: Text Processing
Classifier: Topic :: Scientific/Engineering :: Information Analysis
Classifier: Topic :: Text Processing :: Linguistic
Classifier: Natural Language :: English
Classifier: Programming Language :: Python :: 2.7
Classifier: Programming Language :: Python :: 3.6
Classifier: License :: OSI Approved :: Apache Software License
